RetsamEmail/__init__.py
RetsamEmail-0.1.dist-info/METADATA
RetsamEmail-0.1.dist-info/WHEEL
RetsamEmail-0.1.dist-info/top_level.txt
RetsamEmail-0.1.dist-info/RECORD
