Metadata-Version: 2.1
Name: RetsamEmail
Version: 0.1
Summary: This is a test package.
Home-page: UNKNOWN
Author: Retsam
Author-email: ruslan69623@gmail.com
License: UNKNOWN
Platform: UNKNOWN
Classifier: Programming Language :: Python :: 3
Classifier: License :: OSI Approved :: MIT License
Classifier: Operating System :: OS Independent
Requires-Python: >=3.7
Requires-Dist: Django (==3.2.13)
